python_artnet/__init__.py
python_artnet/python_artnet.py
python_artnet-1.2.0.dist-info/LICENSE
python_artnet-1.2.0.dist-info/METADATA
python_artnet-1.2.0.dist-info/WHEEL
python_artnet-1.2.0.dist-info/top_level.txt
python_artnet-1.2.0.dist-info/RECORD
