Metadata-Version: 2.1
Name: python_artnet
Version: 1.2.0
Summary: Easy-to-use and simple python receiver for Art-Net (that also implements device polling).
Author: sciencegey
Maintainer: sciencegey
License: MIT License
Project-URL: Homepage, https://github.com/sciencegey/python_artnet
Project-URL: Repository, https://github.com/sciencegey/python_artnet.git
Project-URL: Issues, https://github.com/sciencegey/python_artnet/issues
Keywords: Art-Net,ArtNet,DMX,Lighting,Lighting Control
Classifier: Development Status :: 4 - Beta
Classifier: Topic :: Software Development :: Libraries :: Python Modules
Classifier: Topic :: Artistic Software
Classifier: Topic :: Multimedia
Classifier: Intended Audience :: Developers
Classifier: Operating System :: OS Independent
Classifier: License :: OSI Approved :: MIT License
Classifier: Programming Language :: Python :: 3
Classifier: Programming Language :: Python :: 3.8
Classifier: Programming Language :: Python :: 3.9
Classifier: Programming Language :: Python :: 3.10
Classifier: Programming Language :: Python :: 3.11
Classifier: Programming Language :: Python :: 3.12
Requires-Python: >=3.8
License-File: LICENSE
